awsiot-0.1.2.dist-info/DESCRIPTION.rst
awsiot-0.1.2.dist-info/METADATA
awsiot-0.1.2.dist-info/RECORD
awsiot-0.1.2.dist-info/WHEEL
awsiot-0.1.2.dist-info/entry_points.txt
awsiot-0.1.2.dist-info/metadata.json
awsiot-0.1.2.dist-info/top_level.txt
commands/__init__.py
commands/awsiot.py
factories/__init__.py
factories/aws/__init__.py
factories/aws/thing.py
factories/aws/thingtype.py
