Metadata-Version: 2.0
Name: awsiot
Version: 0.1.2
Summary: Command Line utility to easily provision IoT things in AWS
Home-page: https://github.com/adamsondelacruz/awsiot
Author: Adamson dela Cruz
Author-email: adamson.delacruz@gmail.com
License: MIT
Keywords: aws iot
Platform: UNKNOWN
Classifier: Development Status :: 3 - Alpha
Classifier: Intended Audience :: Developers
Classifier: Topic :: Utilities
Classifier: License :: OSI Approved :: MIT License
Classifier: Programming Language :: Python :: 3
Classifier: Programming Language :: Python :: 3.3
Classifier: Programming Language :: Python :: 3.4
Classifier: Programming Language :: Python :: 3.5
Classifier: Programming Language :: Python :: 3.6
Requires-Dist: boto3
Requires-Dist: botocore
Requires-Dist: click
